[
  {
    "type": "function",
    "name": "ADMIN_ROLE",
    "inputs": [],
    "outputs": [
      {
        "name": "",
        "type": "bytes32",
        "internalType": "bytes32"
      }
    ],
    "stateMutability": "view"
  },
  {
    "type": "function",
    "name": "DEFAULT_ADMIN_ROLE",
    "inputs": [],
    "outputs": [
      {
        "name": "",
        "type": "bytes32",
        "internalType": "bytes32"
      }
    ],
    "stateMutability": "view"
  },
  {
    "type": "function",
    "name": "OHM",
    "inputs": [],
    "outputs": [
      {
        "name": "",
        "type": "address",
        "internalType": "address"
      }
    ],
    "stateMutability": "view"
  },
  {
    "type": "function",
    "name": "claimInterest",
    "inputs": [
      {
        "name": "_amount",
        "type": "uint256",
        "internalType": "uint256"
      },
      {
        "name": "_lockIndex",
        "type": "uint8",
        "internalType": "uint8"
      }
    ],
    "outputs": [],
    "stateMutability": "nonpayable"
  },
  {
    "type": "function",
    "name": "conversionRatio",
    "inputs": [],
    "outputs": [
      {
        "name": "",
        "type": "uint256",
        "internalType": "uint256"
      }
    ],
    "stateMutability": "view"
  },
  {
    "type": "function",
    "name": "convert",
    "inputs": [
      {
        "name": "_fromAmount",
        "type": "uint256",
        "internalType": "uint256"
      }
    ],
    "outputs": [],
    "stateMutability": "nonpayable"
  },
  {
    "type": "function",
    "name": "fromToken",
    "inputs": [],
    "outputs": [
      {
        "name": "",
        "type": "address",
        "internalType": "address"
      }
    ],
    "stateMutability": "view"
  },
  {
    "type": "function",
    "name": "getConvertAmount",
    "inputs": [
      {
        "name": "_fromAmount",
        "type": "uint256",
        "internalType": "uint256"
      }
    ],
    "outputs": [
      {
        "name": "",
        "type": "uint256",
        "internalType": "uint256"
      }
    ],
    "stateMutability": "view"
  },
  {
    "type": "function",
    "name": "getRoleAdmin",
    "inputs": [
      {
        "name": "role",
        "type": "bytes32",
        "internalType": "bytes32"
      }
    ],
    "outputs": [
      {
        "name": "",
        "type": "bytes32",
        "internalType": "bytes32"
      }
    ],
    "stateMutability": "view"
  },
  {
    "type": "function",
    "name": "grantRole",
    "inputs": [
      {
        "name": "role",
        "type": "bytes32",
        "internalType": "bytes32"
      },
      {
        "name": "account",
        "type": "address",
        "internalType": "address"
      }
    ],
    "outputs": [],
    "stateMutability": "nonpayable"
  },
  {
    "type": "function",
    "name": "hasRole",
    "inputs": [
      {
        "name": "role",
        "type": "bytes32",
        "internalType": "bytes32"
      },
      {
        "name": "account",
        "type": "address",
        "internalType": "address"
      }
    ],
    "outputs": [
      {
        "name": "",
        "type": "bool",
        "internalType": "bool"
      }
    ],
    "stateMutability": "view"
  },
  {
    "type": "function",
    "name": "initialize",
    "inputs": [
      {
        "name": "_OHM",
        "type": "address",
        "internalType": "address"
      },
      {
        "name": "_sOHM",
        "type": "address",
        "internalType": "address"
      },
      {
        "name": "_network",
        "type": "address",
        "internalType": "address"
      },
      {
        "name": "_staking",
        "type": "address",
        "internalType": "address"
      },
      {
        "name": "_yieldLocker",
        "type": "address",
        "internalType": "address"
      },
      {
        "name": "_term",
        "type": "uint256",
        "internalType": "uint256"
      },
      {
        "name": "_warmupBlocks",
        "type": "uint256",
        "internalType": "uint256"
      }
    ],
    "outputs": [],
    "stateMutability": "nonpayable"
  },
  {
    "type": "function",
    "name": "listStake",
    "inputs": [
      {
        "name": "_user",
        "type": "address",
        "internalType": "address"
      }
    ],
    "outputs": [
      {
        "name": "",
        "type": "tuple",
        "internalType": "struct MappingStaking.ListStake",
        "components": [
          {
            "name": "pending",
            "type": "uint256",
            "internalType": "uint256"
          },
          {
            "name": "blockReward",
            "type": "uint256",
            "internalType": "uint256"
          },
          {
            "name": "extraInterest",
            "type": "uint256",
            "internalType": "uint256"
          },
          {
            "name": "claimableBalance",
            "type": "uint256",
            "internalType": "uint256"
          },
          {
            "name": "expiry",
            "type": "uint256",
            "internalType": "uint256"
          }
        ]
      }
    ],
    "stateMutability": "view"
  },
  {
    "type": "function",
    "name": "network",
    "inputs": [],
    "outputs": [
      {
        "name": "",
        "type": "address",
        "internalType": "address"
      }
    ],
    "stateMutability": "view"
  },
  {
    "type": "function",
    "name": "pause",
    "inputs": [],
    "outputs": [],
    "stateMutability": "nonpayable"
  },
  {
    "type": "function",
    "name": "paused",
    "inputs": [],
    "outputs": [
      {
        "name": "",
        "type": "bool",
        "internalType": "bool"
      }
    ],
    "stateMutability": "view"
  },
  {
    "type": "function",
    "name": "pendingPayout",
    "inputs": [
      {
        "name": "_user",
        "type": "address",
        "internalType": "address"
      }
    ],
    "outputs": [
      {
        "name": "",
        "type": "uint256",
        "internalType": "uint256"
      }
    ],
    "stateMutability": "view"
  },
  {
    "type": "function",
    "name": "renounceRole",
    "inputs": [
      {
        "name": "role",
        "type": "bytes32",
        "internalType": "bytes32"
      },
      {
        "name": "callerConfirmation",
        "type": "address",
        "internalType": "address"
      }
    ],
    "outputs": [],
    "stateMutability": "nonpayable"
  },
  {
    "type": "function",
    "name": "revokeRole",
    "inputs": [
      {
        "name": "role",
        "type": "bytes32",
        "internalType": "bytes32"
      },
      {
        "name": "account",
        "type": "address",
        "internalType": "address"
      }
    ],
    "outputs": [],
    "stateMutability": "nonpayable"
  },
  {
    "type": "function",
    "name": "sOHM",
    "inputs": [],
    "outputs": [
      {
        "name": "",
        "type": "address",
        "internalType": "address"
      }
    ],
    "stateMutability": "view"
  },
  {
    "type": "function",
    "name": "setContract",
    "inputs": [
      {
        "name": "_contract",
        "type": "uint8",
        "internalType": "enum MappingStaking.CONTRACTS"
      },
      {
        "name": "_address",
        "type": "address",
        "internalType": "address"
      }
    ],
    "outputs": [],
    "stateMutability": "nonpayable"
  },
  {
    "type": "function",
    "name": "setFromToken",
    "inputs": [
      {
        "name": "_fromToken",
        "type": "address",
        "internalType": "address"
      }
    ],
    "outputs": [],
    "stateMutability": "nonpayable"
  },
  {
    "type": "function",
    "name": "setTerm",
    "inputs": [
      {
        "name": "_term",
        "type": "uint256",
        "internalType": "uint256"
      }
    ],
    "outputs": [],
    "stateMutability": "nonpayable"
  },
  {
    "type": "function",
    "name": "setWarmupBlocks",
    "inputs": [
      {
        "name": "_warmupBlocks",
        "type": "uint256",
        "internalType": "uint256"
      }
    ],
    "outputs": [],
    "stateMutability": "nonpayable"
  },
  {
    "type": "function",
    "name": "stake",
    "inputs": [
      {
        "name": "_hash",
        "type": "bytes32",
        "internalType": "bytes32"
      },
      {
        "name": "_stakers",
        "type": "address[]",
        "internalType": "address[]"
      },
      {
        "name": "_amounts",
        "type": "uint256[]",
        "internalType": "uint256[]"
      }
    ],
    "outputs": [],
    "stateMutability": "nonpayable"
  },
  {
    "type": "function",
    "name": "stakes",
    "inputs": [
      {
        "name": "",
        "type": "address",
        "internalType": "address"
      }
    ],
    "outputs": [
      {
        "name": "principal",
        "type": "uint256",
        "internalType": "uint256"
      },
      {
        "name": "gons",
        "type": "uint256",
        "internalType": "uint256"
      },
      {
        "name": "startEpoch",
        "type": "uint256",
        "internalType": "uint256"
      },
      {
        "name": "expiry",
        "type": "uint256",
        "internalType": "uint256"
      },
      {
        "name": "warmup",
        "type": "uint256",
        "internalType": "uint256"
      },
      {
        "name": "lastBlock",
        "type": "uint256",
        "internalType": "uint256"
      },
      {
        "name": "vesting",
        "type": "uint256",
        "internalType": "uint256"
      },
      {
        "name": "exists",
        "type": "bool",
        "internalType": "bool"
      }
    ],
    "stateMutability": "view"
  },
  {
    "type": "function",
    "name": "staking",
    "inputs": [],
    "outputs": [
      {
        "name": "",
        "type": "address",
        "internalType": "address"
      }
    ],
    "stateMutability": "view"
  },
  {
    "type": "function",
    "name": "supportsInterface",
    "inputs": [
      {
        "name": "interfaceId",
        "type": "bytes4",
        "internalType": "bytes4"
      }
    ],
    "outputs": [
      {
        "name": "",
        "type": "bool",
        "internalType": "bool"
      }
    ],
    "stateMutability": "view"
  },
  {
    "type": "function",
    "name": "term",
    "inputs": [],
    "outputs": [
      {
        "name": "",
        "type": "uint256",
        "internalType": "uint256"
      }
    ],
    "stateMutability": "view"
  },
  {
    "type": "function",
    "name": "unpause",
    "inputs": [],
    "outputs": [],
    "stateMutability": "nonpayable"
  },
  {
    "type": "function",
    "name": "unstakePrincipal",
    "inputs": [],
    "outputs": [],
    "stateMutability": "nonpayable"
  },
  {
    "type": "function",
    "name": "warmupBlocks",
    "inputs": [],
    "outputs": [
      {
        "name": "",
        "type": "uint256",
        "internalType": "uint256"
      }
    ],
    "stateMutability": "view"
  },
  {
    "type": "function",
    "name": "yieldLocker",
    "inputs": [],
    "outputs": [
      {
        "name": "",
        "type": "address",
        "internalType": "address"
      }
    ],
    "stateMutability": "view"
  },
  {
    "type": "event",
    "name": "BatchStaked",
    "inputs": [
      {
        "name": "operator",
        "type": "address",
        "indexed": true,
        "internalType": "address"
      },
      {
        "name": "_hash",
        "type": "bytes32",
        "indexed": false,
        "internalType": "bytes32"
      },
      {
        "name": "timestamp",
        "type": "uint256",
        "indexed": false,
        "internalType": "uint256"
      }
    ],
    "anonymous": false
  },
  {
    "type": "event",
    "name": "Converted",
    "inputs": [
      {
        "name": "_user",
        "type": "address",
        "indexed": true,
        "internalType": "address"
      },
      {
        "name": "_fromAmount",
        "type": "uint256",
        "indexed": false,
        "internalType": "uint256"
      },
      {
        "name": "_toAmount",
        "type": "uint256",
        "indexed": false,
        "internalType": "uint256"
      },
      {
        "name": "_times",
        "type": "uint256",
        "indexed": false,
        "internalType": "uint256"
      }
    ],
    "anonymous": false
  },
  {
    "type": "event",
    "name": "Initialized",
    "inputs": [
      {
        "name": "version",
        "type": "uint64",
        "indexed": false,
        "internalType": "uint64"
      }
    ],
    "anonymous": false
  },
  {
    "type": "event",
    "name": "InterestClaimed",
    "inputs": [
      {
        "name": "_user",
        "type": "address",
        "indexed": true,
        "internalType": "address"
      },
      {
        "name": "_amount",
        "type": "uint256",
        "indexed": false,
        "internalType": "uint256"
      },
      {
        "name": "_lockIndex",
        "type": "uint8",
        "indexed": false,
        "internalType": "uint8"
      },
      {
        "name": "timestamp",
        "type": "uint256",
        "indexed": false,
        "internalType": "uint256"
      }
    ],
    "anonymous": false
  },
  {
    "type": "event",
    "name": "RoleAdminChanged",
    "inputs": [
      {
        "name": "role",
        "type": "bytes32",
        "indexed": true,
        "internalType": "bytes32"
      },
      {
        "name": "previousAdminRole",
        "type": "bytes32",
        "indexed": true,
        "internalType": "bytes32"
      },
      {
        "name": "newAdminRole",
        "type": "bytes32",
        "indexed": true,
        "internalType": "bytes32"
      }
    ],
    "anonymous": false
  },
  {
    "type": "event",
    "name": "RoleGranted",
    "inputs": [
      {
        "name": "role",
        "type": "bytes32",
        "indexed": true,
        "internalType": "bytes32"
      },
      {
        "name": "account",
        "type": "address",
        "indexed": true,
        "internalType": "address"
      },
      {
        "name": "sender",
        "type": "address",
        "indexed": true,
        "internalType": "address"
      }
    ],
    "anonymous": false
  },
  {
    "type": "event",
    "name": "RoleRevoked",
    "inputs": [
      {
        "name": "role",
        "type": "bytes32",
        "indexed": true,
        "internalType": "bytes32"
      },
      {
        "name": "account",
        "type": "address",
        "indexed": true,
        "internalType": "address"
      },
      {
        "name": "sender",
        "type": "address",
        "indexed": true,
        "internalType": "address"
      }
    ],
    "anonymous": false
  },
  {
    "type": "event",
    "name": "Staked",
    "inputs": [
      {
        "name": "_user",
        "type": "address",
        "indexed": true,
        "internalType": "address"
      },
      {
        "name": "_amount",
        "type": "uint256",
        "indexed": false,
        "internalType": "uint256"
      },
      {
        "name": "timestamp",
        "type": "uint256",
        "indexed": false,
        "internalType": "uint256"
      }
    ],
    "anonymous": false
  },
  {
    "type": "event",
    "name": "TaxTransfer",
    "inputs": [
      {
        "name": "_user",
        "type": "address",
        "indexed": true,
        "internalType": "address"
      },
      {
        "name": "_amount",
        "type": "uint256",
        "indexed": false,
        "internalType": "uint256"
      },
      {
        "name": "timestamp",
        "type": "uint256",
        "indexed": false,
        "internalType": "uint256"
      }
    ],
    "anonymous": false
  },
  {
    "type": "event",
    "name": "Unstaked",
    "inputs": [
      {
        "name": "_user",
        "type": "address",
        "indexed": true,
        "internalType": "address"
      },
      {
        "name": "_amount",
        "type": "uint256",
        "indexed": false,
        "internalType": "uint256"
      },
      {
        "name": "timestamp",
        "type": "uint256",
        "indexed": false,
        "internalType": "uint256"
      }
    ],
    "anonymous": false
  },
  {
    "type": "error",
    "name": "AccessControlBadConfirmation",
    "inputs": []
  },
  {
    "type": "error",
    "name": "AccessControlUnauthorizedAccount",
    "inputs": [
      {
        "name": "account",
        "type": "address",
        "internalType": "address"
      },
      {
        "name": "neededRole",
        "type": "bytes32",
        "internalType": "bytes32"
      }
    ]
  },
  {
    "type": "error",
    "name": "AlreadyExists",
    "inputs": []
  },
  {
    "type": "error",
    "name": "AmountExceedsAvailableInterest",
    "inputs": []
  },
  {
    "type": "error",
    "name": "AmountZero",
    "inputs": []
  },
  {
    "type": "error",
    "name": "InsufficientBalance",
    "inputs": []
  },
  {
    "type": "error",
    "name": "InvalidAmount",
    "inputs": []
  },
  {
    "type": "error",
    "name": "InvalidData",
    "inputs": []
  },
  {
    "type": "error",
    "name": "InvalidInitialization",
    "inputs": []
  },
  {
    "type": "error",
    "name": "NoPrincipalToUnstake",
    "inputs": []
  },
  {
    "type": "error",
    "name": "NotAllowed",
    "inputs": []
  },
  {
    "type": "error",
    "name": "NotInitializing",
    "inputs": []
  },
  {
    "type": "error",
    "name": "Paused",
    "inputs": []
  },
  {
    "type": "error",
    "name": "PrincipalExceedsInterestBalance",
    "inputs": []
  },
  {
    "type": "error",
    "name": "SafeERC20FailedOperation",
    "inputs": [
      {
        "name": "token",
        "type": "address",
        "internalType": "address"
      }
    ]
  },
  {
    "type": "error",
    "name": "SenderNotActive",
    "inputs": []
  },
  {
    "type": "error",
    "name": "StakeFailure",
    "inputs": []
  },
  {
    "type": "error",
    "name": "StakeNotExist",
    "inputs": []
  },
  {
    "type": "error",
    "name": "StillInWarmupPeriod",
    "inputs": []
  }
]
